{"type":"Topology","objects":{"collection":{"type":"GeometryCollection","geometries":[{"type":"Polygon","arcs":[[0]],"properties":{"irwinid":"{01A26525-F24B-42F8-A6FB-0EE890886701}","mapmethod":"Other","unitIDProt":"ORVAD","unitIDOwn":"ORVAD","incidentID":"2017-ORVAD-000151","fireName":"Haystack Rock","perDatTime":"7/29/2017 8:30:00 AM","comments":"WFDSS; Drawn based off modis and viirs","agency":"BLM","active":"Y","latest":"Y","compParID":null,"fireYear":"2017","dateCrnt":"2017-07-29T07:00:00.000Z","inciwebId":null,"firecode":"K8DS","compfirecd":null,"fireNum":"000151","ComplexNm":null,"state":"OR","mergeid":"{}","inComplex":"N","GISACRES":1267.70681006,"fireReportDate":"2017-07-29T15:30:00.000Z"}}]}},"arcs":[[[-117.31156,43.62161],[-117.31071,43.62682],[-117.30951,43.62967],[-117.3006,43.6355],[-117.29785,43.63724],[-117.29083,43.6417],[-117.28449,43.64195],[-117.27575,43.64765],[-117.26992,43.64629],[-117.26632,43.64406],[-117.26598,43.63897],[-117.26632,43.63649],[-117.27266,43.63339],[-117.27883,43.63277],[-117.28654,43.63178],[-117.29306,43.62657],[-117.31037,43.61478],[-117.31156,43.62161]]],"bbox":[-117.31156,43.61478,-117.26598,43.64765]}